utfcolor/__init__.py
utfcolor/__main__.py
utfcolor/argparams.py
utfcolor/createEncoding.py
utfcolor/main.py
utfcolor/standardEncoding.py
utfcolor/upScale.py
utfcolor/utfcolorv1.py
utfcolor/utfcolorv2.py
utfcolor/utfcolorv3.py
utfcolor/util.py
utfcolor-1.0.0.dist-info/DESCRIPTION.rst
utfcolor-1.0.0.dist-info/METADATA
utfcolor-1.0.0.dist-info/RECORD
utfcolor-1.0.0.dist-info/WHEEL
utfcolor-1.0.0.dist-info/metadata.json
utfcolor-1.0.0.dist-info/top_level.txt
