Metadata-Version: 2.0
Name: utfcolor
Version: 1.0.0
Summary: Convert text to images with Python
Home-page: https://github.com/5omega/utfcolor
Author: 5omega
Author-email: 5omega@posteo.de
License: MIT
Platform: UNKNOWN
Classifier: Programming Language :: Python :: 3
Classifier: License :: OSI Approved :: MIT License
Classifier: Operating System :: OS Independent
Requires-Python: >=3.6.9
Requires-Dist: Pillow (==8.1.2)
